{"url":"https:\/\/trafficmeter.bitrix24.ru\/rest\/40\/ifskn5q31015ekkz\/crm.requisite.add.json","info":{"url":"https:\/\/trafficmeter.bitrix24.ru\/rest\/40\/ifskn5q31015ekkz\/crm.requisite.add.json","content_type":"application\/json; charset=utf-8","http_code":"200","header_size":"1153","request_size":"396","filetime":"-1","ssl_verify_result":"0","redirect_count":"0","total_time":"0.167233","namelookup_time":"1.9E-5","connect_time":"0.008251","pretransfer_time":"0.03697","size_upload":"178","size_download":"272","speed_download":"1628","speed_upload":"1065","download_content_length":"-1","upload_content_length":"178","starttransfer_time":"0.167198","redirect_time":"0","redirect_url":"","primary_ip":"89.208.228.119","certinfo":[],"primary_port":"443","local_ip":"5.23.51.63","local_port":"52708","http_version":"2","protocol":"2","ssl_verifyresult":"0","scheme":"HTTPS"},"params":{"method":"crm.requisite.add","params":{"fields":{"ENTITY_TYPE_ID":"4","ENTITY_ID":"74","TITLE":"TEST","ACTIVE":"Y","PRESET_ID":"1","NAME":"TEST NAME","RQ_INN":"5902300019"}}},"result":{"result":"30","time":{"start":"1669632787.6578","finish":"1669632787.747","duration":"0.089215993881226","processing":"0.050427913665771","date_start":"2022-11-28T13:53:07+03:00","date_finish":"2022-11-28T13:53:07+03:00","operating_reset_at":"1669633387","operating":"0"}}}