{"url":"https:\/\/trafficmeter.bitrix24.ru\/rest\/40\/ifskn5q31015ekkz\/crm.requisite.entity.search.json","info":{"url":"https:\/\/trafficmeter.bitrix24.ru\/rest\/40\/ifskn5q31015ekkz\/crm.requisite.entity.search.json","content_type":"application\/json; charset=utf-8","http_code":"200","header_size":"1149","request_size":"267","filetime":"-1","ssl_verify_result":"0","redirect_count":"0","total_time":"0.168471","namelookup_time":"0.060344","connect_time":"0.061299","pretransfer_time":"0.080429","size_upload":"40","size_download":"282","speed_download":"1678","speed_upload":"238","download_content_length":"-1","upload_content_length":"40","starttransfer_time":"0.168432","redirect_time":"0","redirect_url":"","primary_ip":"178.132.201.50","certinfo":[],"primary_port":"443","local_ip":"5.23.51.63","local_port":"60330","http_version":"2","protocol":"2","ssl_verifyresult":"0","scheme":"HTTPS"},"params":{"method":"crm.requisite.entity.search","params":{"searchQuery":" 123","options":{"presetId":"1"}}},"result":{"result":{"items":[]},"time":{"start":"1669749760.9021","finish":"1669749760.9444","duration":"0.042304039001465","processing":"0.0061590671539307","date_start":"2022-11-29T22:22:40+03:00","date_finish":"2022-11-29T22:22:40+03:00","operating_reset_at":"1669750360","operating":"0"}}}